LICENSE
README.md
setup.cfg
setup.py
src/adfmapping.py
src/adfmapping.egg-info/PKG-INFO
src/adfmapping.egg-info/SOURCES.txt
src/adfmapping.egg-info/dependency_links.txt
src/adfmapping.egg-info/entry_points.txt
src/adfmapping.egg-info/requires.txt
src/adfmapping.egg-info/top_level.txt