Metadata-Version: 2.1
Name: adfmapping
Version: 0.1.1
Summary: A package to create mapping json for  ADF Source Data/columns to Sink Columns.
Home-page: https://github.com/gogi2811/adfmapping
Author: Gaurav Lotekar
Author-email: gauravnlotekar@gmail.com
License: UNKNOWN
Project-URL: Bug Tracker, https://github.com/gogi2811/adfmapping/issues
Keywords: Azure ADF mapping ADF mapping JSON json
Platform: UNKNOWN
Classifier: Programming Language :: Python :: 3
Classifier: License :: OSI Approved :: MIT License
Classifier: Operating System :: OS Independent
Requires-Python: >=3.6
License-File: LICENSE
